rsm4dcm/__init__.py
rsm4dcm/__main__.py
rsm4dcm/rsm4dcm.py
rsm4dcm/tests/__init__.py
rsm4dcm/tests/test_recursive_search.py
rsm4dcm-0.0.2.dist-info/LICENSE
rsm4dcm-0.0.2.dist-info/METADATA
rsm4dcm-0.0.2.dist-info/WHEEL
rsm4dcm-0.0.2.dist-info/top_level.txt
rsm4dcm-0.0.2.dist-info/RECORD
