Metadata-Version: 2.1
Name: rsm4dcm
Version: 0.0.2
Summary: Recursively searches for dicom files & move them where you want.
Home-page: https://github.com/williammadie/tree/master
Author: William Madié
Author-email: william.madie0@gmail.com
License: UNKNOWN
Platform: UNKNOWN
Classifier: Programming Language :: Python :: 3
Classifier: License :: OSI Approved :: MIT License
Classifier: Operating System :: OS Independent
Requires-Python: >=3.6
